blockx_weather/__init__.py
blockx_weather/cli.py
blockx_weather/core.py
blockx_weather-0.1.1.dist-info/licenses/LICENSE
blockx_weather-0.1.1.dist-info/METADATA
blockx_weather-0.1.1.dist-info/WHEEL
blockx_weather-0.1.1.dist-info/entry_points.txt
blockx_weather-0.1.1.dist-info/top_level.txt
blockx_weather-0.1.1.dist-info/RECORD
