Metadata-Version: 2.4
Name: blockx-weather
Version: 0.1.1
Summary: A Python package to fetch current weather data using OpenWeatherMap API
Author-email: Mohit <mohit@blockxint.com>
License: MIT
Project-URL: Homepage, https://github.com/blockx/blockx-weather
Project-URL: Bug Tracker, https://github.com/blockx/blockx-weather/issues
Classifier: Programming Language :: Python :: 3
Classifier: License :: OSI Approved :: MIT License
Classifier: Operating System :: OS Independent
Classifier: Development Status :: 4 - Beta
Classifier: Intended Audience :: Developers
Classifier: Topic :: Software Development :: Libraries :: Python Modules
Classifier: Topic :: Scientific/Engineering :: Atmospheric Science
Requires-Python: >=3.7
License-File: LICENSE
Requires-Dist: requests>=2.25.0
Requires-Dist: python-dotenv>=0.15.0
Dynamic: license-file
